lxml_dataclass/__init__.py
lxml_dataclass/element.py
lxml_dataclass-1.0.6.dist-info/licenses/LICENSE
lxml_dataclass-1.0.6.dist-info/METADATA
lxml_dataclass-1.0.6.dist-info/WHEEL
lxml_dataclass-1.0.6.dist-info/top_level.txt
lxml_dataclass-1.0.6.dist-info/RECORD
