Metadata-Version: 2.4
Name: lxml-dataclass
Version: 1.0.6
Summary: Create LXML Elements as dataclasses representations
Author-email: Sebastian Salinas <seba.salinas.delrio@gmail.com>
License-Expression: MIT
Project-URL: Homepage, https://github.com/sebasalinass/lxml-dataclass
Keywords: lxml,dataclass,xml
Classifier: Programming Language :: Python
Classifier: Programming Language :: Python :: 3
Classifier: Programming Language :: Python :: 3.11
Requires-Python: >=3.11
License-File: LICENSE
Requires-Dist: lxml>=5.4.0
Dynamic: license-file
